thermoengine_utils/__init__.py
thermoengine_utils/coder.py
thermoengine_utils/coder_templates.py
thermoengine_utils/core.py
thermoengine_utils/data/coder/__init__.py
thermoengine_utils/data/coder/berman_1988.json
thermoengine_utils/data/coder/elements.csv
thermoengine_utils/data/coder/entropies.csv
thermoengine_utils-0.3.dist-info/licenses/LICENSE
thermoengine_utils-0.3.dist-info/METADATA
thermoengine_utils-0.3.dist-info/WHEEL
thermoengine_utils-0.3.dist-info/top_level.txt
thermoengine_utils-0.3.dist-info/RECORD
