Metadata-Version: 2.4
Name: thermoengine_utils
Version: 0.3
Summary: Utility Python package for ENKI thermoengine
Author-email: "Aaron S. Wolf" <aswolf@seti.org>, "Mark S. Ghiorso" <ghiorso@ofm-research.org>, "Simon W. Matthews" <simonm@hi.is>
License:                     GNU AFFERO GENERAL PUBLIC LICENSE
Project-URL: Homepage, https://gitlab.com/ENKI-portal/ThermoEngine
Project-URL: Bug Tracker, https://gitlab.com/ENKI-portal/ThermoEngine/-/issues/new
Classifier: Development Status :: 4 - Beta
Classifier: Environment :: Plugins
Classifier: Intended Audience :: Developers
Classifier: Intended Audience :: Education
Classifier: Intended Audience :: Science/Research
Classifier: License :: OSI Approved :: GNU Affero General Public License v3
Classifier: Natural Language :: English
Classifier: Operating System :: OS Independent
Classifier: Programming Language :: Python
Classifier: Topic :: Scientific/Engineering
Classifier: Topic :: Scientific/Engineering :: Chemistry
Classifier: Topic :: Scientific/Engineering :: Mathematics
Classifier: Topic :: Scientific/Engineering :: Physics
Classifier: Topic :: Software Development :: Libraries :: Python Modules
Requires-Python: >=3.10
License-File: LICENSE
Requires-Dist: cython
Requires-Dist: numpy
Requires-Dist: pandas>=1.5.2
Requires-Dist: sympy>=1.11.1
Requires-Dist: scipy>=1.9.3
Dynamic: license-file
